Workbook

Sheet PL設計
A1: 損益計算書（PL）
A2: （単位：円） | B2: FY25 | C2: FY26 | D2: FY27 | E2: FY28 | F2: FY29
A4: 売上高 | B4: ='ミールモデル'!B10+'アカデミーモデル'!B10+'コンサルモデル'!B10 | C4: ='ミールモデル'!C10+'アカデミーモデル'!C10+'コンサルモデル'!C10 | D4: ='ミールモデル'!D10+'アカデミーモデル'!D10+'コンサルモデル'!D10 | E4: ='ミールモデル'!E10+'アカデミーモデル'!E10+'コンサルモデル'!E10 | F4: ='ミールモデル'!F10+'アカデミーモデル'!F10+'コンサルモデル'!F10
A5: 売上原価 | B5: =B4*0.3 | C5: =C4*0.3 | D5: =D4*0.3 | E5: =E4*0.3 | F5: =F4*0.3
A6: 粗利 | B6: =B4-B5 | C6: =C4-C5 | D6: =D4-D5 | E6: =E4-E5 | F6: =F4-F5
A7: 粗利率 | B7: =IF(B4=0,0,B6/B4) | C7: =IF(C4=0,0,C6/C4) | D7: =IF(D4=0,0,D6/D4) | E7: =IF(E4=0,0,E6/E4) | F7: =IF(F4=0,0,F6/F4)
A9: 販管費合計 | B9: ='費用まとめ'!B12 | C9: ='費用まとめ'!C12 | D9: ='費用まとめ'!D12 | E9: ='費用まとめ'!E12 | F9: ='費用まとめ'!F12
A10: 営業利益 | B10: =B6-B9 | C10: =C6-C9 | D10: =D6-D9 | E10: =E6-E9 | F10: =F6-F9
A11: 営業利益率 | B11: =IF(B4=0,0,B10/B4) | C11: =IF(C4=0,0,C10/C4) | D11: =IF(D4=0,0,D10/D4) | E11: =IF(E4=0,0,E10/E4) | F11: =IF(F4=0,0,F10/F4)
A13: EBITDA | B13: =B10+500000 | C13: =C10+500000 | D13: =D10+500000 | E13: =E10+500000 | F13: =F10+500000
A14: EBITDA率 | B14: =IF(B4=0,0,B13/B4) | C14: =IF(C4=0,0,C13/C4) | D14: =IF(D4=0,0,D13/D4) | E14: =IF(E4=0,0,E13/E4) | F14: =IF(F4=0,0,F13/F4)

Sheet ミールモデル
A1: ミールモデル（ユニットエコノミクス）
B2: FY25 | C2: FY26 | D2: FY27 | E2: FY28 | F2: FY29
A3: 顧客数 | B3: 100 | C3: 200 | D3: 350 | E3: 500 | F3: 700
A4: 客単価（円/月） | B4: 5000 | C4: 5000 | D4: 5000 | E4: 5000 | F4: 5000
A5: 月間利用回数 | B5: 4 | C5: 4 | D5: 4 | E5: 4 | F5: 4
A6: 解約率（月次） | B6: 0.03 | C6: 0.03 | D6: 0.025 | E6: 0.025 | F6: 0.02
A7: 月次売上 | B7: =B3*B4 | C7: =C3*C4 | D7: =D3*D4 | E7: =E3*E4 | F7: =F3*F4
A8: 年間売上 | B8: =B7*12 | C8: =C7*12 | D8: =D7*12 | E8: =E7*12 | F8: =F7*12
A9: LTV | B9: =IF(B6=0,0,B4/B6) | C9: =IF(C6=0,0,C4/C6) | D9: =IF(D6=0,0,D4/D6) | E9: =IF(E6=0,0,E4/E6) | F9: =IF(F6=0,0,F4/F6)
A10: 売上高 | B10: =B8 | C10: =C8 | D10: =D8 | E10: =E8 | F10: =F8

Sheet アカデミーモデル
A1: アカデミーモデル（教育事業）
B2: FY25 | C2: FY26 | D2: FY27 | E2: FY28 | F2: FY29
A3: 受講者数 | B3: 30 | C3: 60 | D3: 100 | E3: 160 | F3: 250
A4: 講座単価 | B4: 30000 | C4: 30000 | D4: 32000 | E4: 32000 | F4: 35000
A5: 開催回数/月 | B5: 2 | C5: 2 | D5: 3 | E5: 3 | F5: 4
A6: コンテンツ数 | B6: 5 | C6: 10 | D6: 18 | E6: 25 | F6: 35
A7: 月次売上 | B7: =B3*B4 | C7: =C3*C4 | D7: =D3*D4 | E7: =E3*E4 | F7: =F3*F4
A8: 年間売上 | B8: =B7*12 | C8: =C7*12 | D8: =D7*12 | E8: =E7*12 | F8: =F7*12
A10: 売上高 | B10: =B8 | C10: =C8 | D10: =D8 | E10: =E8 | F10: =F8

Sheet コンサルモデル
A1: コンサルモデル（フライホイール）
B2: FY25 | C2: FY26 | D2: FY27 | E2: FY28 | F2: FY29
A3: コンサルタント数 | B3: 3 | C3: 5 | D3: 8 | E3: 12 | F3: 18
A4: 月間案件数/人 | B4: 2 | C4: 2 | D4: 3 | E4: 3 | F4: 3
A5: 案件単価 | B5: 500000 | C5: 500000 | D5: 600000 | E5: 600000 | F5: 700000
A6: 稼働率 | B6: 0.7 | C6: 0.75 | D6: 0.8 | E6: 0.85 | F6: 0.85
A7: 月次売上 | B7: =B3*B4*B5*B6 | C7: =C3*C4*C5*C6 | D7: =D3*D4*D5*D6 | E7: =E3*E4*E5*E6 | F7: =F3*F4*F5*F6
A8: 年間売上 | B8: =B7*12 | C8: =C7*12 | D8: =D7*12 | E8: =E7*12 | F8: =F7*12
A10: 売上高 | B10: =B8 | C10: =C8 | D10: =D8 | E10: =E8 | F10: =F8

Sheet 費用まとめ
A1: 費用まとめ（SGA）
B2: FY25 | C2: FY26 | D2: FY27 | E2: FY28 | F2: FY29
A4: 人件費合計 | B4: ='費用リスト'!B8 | C4: ='費用リスト'!C8 | D4: ='費用リスト'!D8 | E4: ='費用リスト'!E8 | F4: ='費用リスト'!F8
A5: オフィス費 | B5: ='費用リスト'!B13 | C5: ='費用リスト'!C13 | D5: ='費用リスト'!D13 | E5: ='費用リスト'!E13 | F5: ='費用リスト'!F13
A6: マーケティング費 | B6: ='費用リスト'!B18 | C6: ='費用リスト'!C18 | D6: ='費用リスト'!D18 | E6: ='費用リスト'!E18 | F6: ='費用リスト'!F18
A7: システム費 | B7: ='費用リスト'!B23 | C7: ='費用リスト'!C23 | D7: ='費用リスト'!D23 | E7: ='費用リスト'!E23 | F7: ='費用リスト'!F23
A8: その他 | B8: ='費用リスト'!B27 | C8: ='費用リスト'!C27 | D8: ='費用リスト'!D27 | E8: ='費用リスト'!E27 | F8: ='費用リスト'!F27
A10: 販管費小計 | B10: =SUM(B4:B8) | C10: =SUM(C4:C8) | D10: =SUM(D4:D8) | E10: =SUM(E4:E8) | F10: =SUM(F4:F8)
A11: 予備費（5%） | B11: =B10*0.05 | C11: =C10*0.05 | D11: =D10*0.05 | E11: =E10*0.05 | F11: =F10*0.05
A12: 販管費合計 | B12: =B10+B11 | C12: =C10+C11 | D12: =D10+D11 | E12: =E10+E11 | F12: =F10+F11

Sheet 費用リスト
A1: 費用リスト（詳細）
B2: FY25 | C2: FY26 | D2: FY27 | E2: FY28 | F2: FY29
A3: 【人件費】
A4: 役員報酬 | B4: 6000000 | C4: 7200000 | D4: 8400000 | E4: 9600000 | F4: 12000000
A5: エンジニア人件費 | B5: 4800000 | C5: 9600000 | D5: 16800000 | E5: 24000000 | F5: 33600000
A6: 営業人件費 | B6: 3600000 | C6: 7200000 | D6: 10800000 | E6: 14400000 | F6: 21600000
A7: その他人件費 | B7: 1200000 | C7: 2400000 | D7: 3600000 | E7: 4800000 | F7: 7200000
A8: 人件費小計 | B8: =SUM(B4:B7) | C8: =SUM(C4:C7) | D8: =SUM(D4:D7) | E8: =SUM(E4:E7) | F8: =SUM(F4:F7)
A9: 【オフィス】
A10: 家賃 | B10: 1200000 | C10: 1200000 | D10: 2400000 | E10: 2400000 | F10: 3600000
A11: 光熱費 | B11: 120000 | C11: 144000 | D11: 240000 | E11: 288000 | F11: 360000
A12: 備品・消耗品 | B12: 180000 | C12: 240000 | D12: 360000 | E12: 480000 | F12: 600000
A13: オフィス小計 | B13: =SUM(B10:B12) | C13: =SUM(C10:C12) | D13: =SUM(D10:D12) | E13: =SUM(E10:E12) | F13: =SUM(F10:F12)
A14: 【マーケティング】
A15: 広告費 | B15: 600000 | C15: 1200000 | D15: 2400000 | E15: 3600000 | F15: 4800000
A16: PR費 | B16: 240000 | C16: 480000 | D16: 720000 | E16: 960000 | F16: 1200000
A17: イベント費 | B17: 120000 | C17: 240000 | D17: 480000 | E17: 720000 | F17: 960000
A18: マーケティング小計 | B18: =SUM(B15:B17) | C18: =SUM(C15:C17) | D18: =SUM(D15:D17) | E18: =SUM(E15:E17) | F18: =SUM(F15:F17)
A19: 【システム】
A20: サーバー費 | B20: 360000 | C20: 600000 | D20: 960000 | E20: 1440000 | F20: 1800000
A21: ツール費 | B21: 240000 | C21: 360000 | D21: 480000 | E21: 720000 | F21: 960000
A22: 外注開発費 | B22: 600000 | C22: 1200000 | D22: 1800000 | E22: 2400000 | F22: 3000000
A23: システム小計 | B23: =SUM(B20:B22) | C23: =SUM(C20:C22) | D23: =SUM(D20:D22) | E23: =SUM(E20:E22) | F23: =SUM(F20:F22)
A24: 【その他】
A25: 交通費 | B25: 180000 | C25: 360000 | D25: 540000 | E25: 720000 | F25: 960000
A26: 顧問・士業費 | B26: 600000 | C26: 600000 | D26: 900000 | E26: 1200000 | F26: 1500000
A27: その他小計 | B27: =SUM(B25:B26) | C27: =SUM(C25:C26) | D27: =SUM(D25:D26) | E27: =SUM(E25:E26) | F27: =SUM(F25:F26)

Sheet 費用タグ
A1: 費用タグ（カテゴリ分類）
A2: 費用項目 | B2: カテゴリ | C2: タグ
A3: 役員報酬 | B3: 人件費 | C3: 固定費
A4: エンジニア人件費 | B4: 人件費 | C4: 固定費
A5: 営業人件費 | B5: 人件費 | C5: 固定費
A6: その他人件費 | B6: 人件費 | C6: 固定費
A7: 家賃 | B7: オフィス | C7: 固定費
A8: 光熱費 | B8: オフィス | C8: 固定費
A9: 備品・消耗品 | B9: オフィス | C9: 変動費
A10: 広告費 | B10: マーケティング | C10: 変動費
A11: PR費 | B11: マーケティング | C11: 変動費
A12: イベント費 | B12: マーケティング | C12: 変動費
A13: サーバー費 | B13: システム | C13: 変動費
... A17: 顧問・士業費 | B17: その他 | C17: 固定費

Sheet （全Ver）前提条件
A1: 前提条件・マクロ仮定
A2: 項目 | B2: 値 | C2: 備考
A3: 市場規模（TAM） | B3: 500億円 | C3: ヘルスケア×教育市場
A4: 市場成長率（年率） | B4: 15% | C4: 業界レポート参照
A5: ターゲットシェア（5年後） | B5: 0.5% | C5: 保守的見積もり
A6: 顧客獲得コスト（CAC） | B6: 15,000円 | C6: 広告・営業含む
A7: 平均契約期間 | B7: 18ヶ月 | C7: 過去実績ベース
A8: 売上原価率 | B8: 30% | C8: 食材・講師・外注費
A9: 人件費成長率 | B9: 20%/年 | C9: 採用計画連動
A10: 為替前提 | B10: 150円/$ | C10: 経営計画ベース
A11: 消費税率 | B11: 10% | C11: 現行税制
A12: 法人税実効税率 | B12: 30% | C12: 中小企業前提
A13: 割引率（WACC） | B13: 10% | C13: DCF計算用
A14: ターミナル成長率 | B14: 2% | C14: 永続成長前提
